processq/__init__.py
processq/__version__.py
processq/process_queue.py
processq/worker_process.py
processq-0.0.1.dist-info/METADATA
processq-0.0.1.dist-info/WHEEL
processq-0.0.1.dist-info/licenses/LICENSE.txt
processq-0.0.1.dist-info/RECORD
