Metadata-Version: 2.1
Name: processq
Version: 0.0.1
Summary: Process Queue
Project-URL: Homepage, https://github.com/haiz/processq
Project-URL: Documentation, https://github.com/haiz/processq/blob/main/README.md
Project-URL: Changelog, https://github.com/haiz/processq/blob/main/CHANGELOG.md
Project-URL: Examples, https://github.com/haiz/processq/blob/main/examples
Project-URL: Source, https://github.com/haiz/processq
Author-email: Hai Cao <cthai83@gmail.com>
License: MIT License
License-File: LICENSE.txt
Keywords: process,queue
Classifier: Development Status :: 4 - Beta
Classifier: Environment :: Web Environment
Classifier: Intended Audience :: Developers
Classifier: License :: OSI Approved :: MIT License
Classifier: Operating System :: OS Independent
Classifier: Programming Language :: Python :: 3
Classifier: Programming Language :: Python :: 3 :: Only
Classifier: Programming Language :: Python :: 3.7
Classifier: Programming Language :: Python :: 3.8
Classifier: Programming Language :: Python :: 3.9
Classifier: Programming Language :: Python :: 3.10
Classifier: Programming Language :: Python :: 3.11
Classifier: Topic :: Software Development :: Libraries
Requires-Python: >=3.7
Provides-Extra: test
Requires-Dist: pytest>=6.0; extra == 'test'
